shredword/shredword/__init__.py
shredword/shredword/cbase.py
shredword/shredword/libtrainer.dll.a
shredword/shredword/libtrainer.pyd
shredword/shredword/trainer.py
shredword/shredword/utils/bpe.py
shredword/shredword/utils/unigram.py
shredword/shredword/utils/utils.py
shredword_trainer-0.1.0.dist-info/METADATA
shredword_trainer-0.1.0.dist-info/WHEEL
shredword_trainer-0.1.0.dist-info/licenses/LICENSE
shredword_trainer-0.1.0.dist-info/RECORD
