Metadata-Version: 2.2
Name: shredword-trainer
Version: 0.1.0
Summary: BPE & Unigram trainer for Shredword tokenizer
Author-Email: Shivendra S <shivharsh44@gmail.com>
License: MIT
Classifier: Development Status :: 5 - Production/Stable
Classifier: Intended Audience :: Developers
Classifier: Programming Language :: Python :: 3
Classifier: Programming Language :: Python :: 3.11
Classifier: Programming Language :: Python :: 3.12
Classifier: Programming Language :: Python :: 3.13
Classifier: Programming Language :: C
Classifier: Programming Language :: C++
Classifier: Operating System :: OS Independent
Requires-Python: >=3.11
